<biblioteca>
    <cancion nombre="Heroes Tonight">
        <artista>"artista1" </artista>
        <album> "album1"</album>
        <imagen> "../Img/heroes.png"</imagen>
        <ruta>"../Musica/heroes.mp3"</ruta>
    </cancion>
    <cancion nombre="alone">
        <artista>"artista1"</artista>
        <album> "album1"</album>,
        <imagen> "../Img/alone.png"</imagen>
        <ruta>"../Musica/alone.mp3"</ruta>
    </cancion>
    <cancion nombre="faded">,
        <artista>"artista2"</artista>
        <album> "album2"</album>,
        <imagen> "../Img/faded.png"</imagen>
        <ruta>"../Musica/faded.mp3"</ruta>
    </cancion>
    <cancion nombre="hhh">,
        <artista>"artista2"   </artista>
        <album> "album2"</album>,
        <imagen> "../Img/faded.png"</imagen>
        <ruta>"../Musica/faded.mp3"</ruta>
    </cancion>
    <cancion nombre="aaa">,
        <artista>"artista3"</artista>
        <album> "album3"</album>,
        <imagen> "../Img/faded.png"</imagen>
        <ruta>"../Musica/faded.mp3"</ruta>
    </cancion>
    <cancion nombre="eee">,
        <artista>"artista4"</artista>
        <album> "album4"</album>,
        <imagen> "../Img/faded.png"</imagen>
        <ruta>"../Musica/faded.mp3"</ruta>
    </cancion>
    <cancion nombre="rrr">,
        <artista>"artista1" </artista>
        <album> "album1"</album>,
        <imagen> "../Img/faded.png"</imagen>
        <ruta>"../Musica/faded.mp3"</ruta>
    </cancion>
    <cancion nombre="jajaja">,
        <artista>"artista5"</artista>
        <album> "album5"</album>,
        <imagen> "../Img/faded.png"</imagen>
        <ruta>"../Musica/faded.mp3"</ruta>
    </cancion>
    <cancion nombre="ppp">
        <artista>"artista1" </artista>
        <album> "album6"</album>
        <imagen> "../Img/heroes.png"</imagen>
        <ruta>"../Musica/heroes.mp3"</ruta>
    </cancion>
    <cancion nombre="ttt">
        <artista> "artista2" </artista>
        <album> "album7"</album>
        <imagen> "../Img/heroes.png"</imagen>
        <ruta>"../Musica/heroes.mp3"</ruta>
    </cancion>
    <cancion nombre="lll">
        <artista>"artista1" </artista>
        <album> "album8"</album>
        <imagen> "../Img/heroes.png"</imagen>
        <ruta>"../Musica/heroes.mp3"</ruta>
    </cancion>
    <cancion nombre="www">
        <artista> "artista3" </artista>
        <album> "album9"</album>
        <imagen> "../Img/heroes.png"</imagen>
        <ruta>"../Musica/heroes.mp3"</ruta>
    </cancion>



</biblioteca>